Easify/__init__.py
Easify/main.py
easify-1.0.6.dist-info/licenses/LICENSE
easify-1.0.6.dist-info/METADATA
easify-1.0.6.dist-info/WHEEL
easify-1.0.6.dist-info/entry_points.txt
easify-1.0.6.dist-info/top_level.txt
easify-1.0.6.dist-info/RECORD
